{
  "dates": [2000, 2001, 2002, 2003, 2004, 2005, 2006, 2007, 2008, 2009, 2010, 2011, 2012, 2013, 2014],

  "states": [
    {
      "name": "District of Columbia",
      "code": "DC",
      "rates": [41.8, 40.3, 46.4, 44.7, 35.7, 33.5, 29.1, 30.8, 31.4, 24.2, 21.8, 17.4, 13.9, 15.9, 15.9]
    },
    {
      "name": "Puerto Rico",
      "code": "PR",
      "rates": [18.22, 19.57, 20.48, 20.69, 21.02, 20.39, 19.82, 19.41, 21.47, 23.82, 26.22, 30.6, 26.46, null, null]
    },
    {
      "name": "Louisiana",
      "code": "LA",
      "rates": [12.5, 11.2, 13.2, 13.0, 12.7, 10.0, 12.9, 14.6, 12.3, 11.8, 11.0, 11.1, 10.6, 10.7, 10.3]
    },
    {
      "name": "New Mexico",
      "code": "NM",
      "rates": [7.4, 5.4, 8.2, 6.2, 8.9, 7.5, 6.9, 9.3, 8.1, 9.9, 6.8, 7.6, 5.6, 5.9, 4.8]
    },
    {
      "name": "Maryland",
      "code": "MD",
      "rates": [8.1, 8.3, 9.4, 9.5, 9.4, 9.9, 9.7, 9.9, 8.8, 7.7, 7.4, 6.8, 6.3, 6.5, 6.1]
    },
    {
      "name": "Tennessee",
      "code": "TN",
      "rates": [7.2, 7.4, 7.3, 6.8, 6.1, 7.2, 6.9, 6.6, 6.6, 7.4, 5.6, 5.9, 6.2, 5.2, 5.7]
    },
    {
      "name": "Alabama",
      "code": "AL",
      "rates": [7.4, 8.5, 6.8, 6.6, 5.6, 8.2, 8.3, 8.9, 7.5, 6.8, 5.7, 6.2, 7.1, 7.2, 5.7]
    },
    {
      "name": "Mississippi",
      "code": "MS",
      "rates": [9.0, 9.9, 9.2, 9.3, 7.8, 7.4, 7.9, 6.9, 8.0, 6.6, 6.9, 7.8, 7.1, 7.3, 8.6]
    },
    {
      "name": "Missouri",
      "code": "MO",
      "rates": [6.2, 6.6, 5.8, 5.1, 6.1, 6.9, 6.3, 6.2, 7.7, 6.5, 7.0, 6.1, 6.5, 6.1, 6.6]
    },
    {
      "name": "Michigan",
      "code": "MI",
      "rates": [6.7, 6.7, 6.8, 6.1, 6.4, 6.2, 7.1, 6.6, 5.5, 6.2, 5.9, 6.2, 7.1, 6.3, 5.4]
    },
    {
      "name": "South Carolina",
      "code": "SC",
      "rates": [7.3, 8.1, 7.3, 7.3, 6.8, 7.4, 8.4, 8.3, 6.9, 6.7, 5.7, 6.8, 7.0, 6.4, 6.4]
    },
    {
      "name": "Arkansas",
      "code": "AR",
      "rates": [6.3, 5.5, 5.2, 6.6, 6.4, 6.8, 7.3, 7.0, 5.8, 6.2, 4.6, 5.4, 5.9, 5.3, 5.6]
    },
    {
      "name": "Oklahoma",
      "code": "OK",
      "rates": [5.3, 5.3, 4.7, 5.9, 5.3, 5.3, 5.9, 6.2, 5.9, 6.3, 5.2, 5.6, 5.8, 5.1, 4.5]
    },
    {
      "name": "Illinois",
      "code": "IL",
      "rates": [7.2, 7.8, 7.6, 7.1, 6.1, 6.0, 6.1, 5.9, 6.1, 6.0, 5.5, 6.1, 6.0, 5.6, 5.3]
    },
    {
      "name": "Nevada",
      "code": "NV",
      "rates": [6.5, 8.6, 8.4, 8.8, 7.4, 8.5, 9.1, 7.5, 6.3, 5.9, 5.8, 5.1, 4.5, 5.8, 6.0]
    },
    {
      "name": "Georgia",
      "code": "GA",
      "rates": [8.0, 7.1, 7.1, 7.6, 6.9, 6.2, 6.5, 7.5, 6.6, 5.8, 5.7, 5.6, 5.9, 5.6, 5.7]
    },
    {
      "name": "Florida",
      "code": "FL",
      "rates": [5.6, 5.3, 5.5, 5.4, 5.4, 5.0, 6.2, 6.6, 6.4, 5.5, 5.2, 5.2, 5.2, 5.0, 5.8]
    },
    {
      "name": "Arizona",
      "code": "AZ",
      "rates": [7.0, 7.5, 7.1, 7.9, 7.2, 7.5, 8.6, 8.6, 7.1, 5.8, 6.4, 6.1, 5.5, 5.4, 4.7]
    },
    {
      "name": "Texas",
      "code": "TX",
      "rates": [5.9, 6.2, 6.0, 6.4, 6.1, 6.1, 5.9, 5.9, 5.6, 5.4, 4.9, 4.4, 4.4, 4.3, 4.4]
    },
    {
      "name": "California",
      "code": "CA",
      "rates": [6.1, 6.4, 6.8, 6.8, 6.7, 6.9, 6.8, 6.2, 5.8, 5.3, 4.8, 4.8, 5.0, 4.5, 4.4]
    },
    {
      "name": "North Carolina",
      "code": "NC",
      "rates": [7.0, 6.2, 6.6, 6.0, 6.2, 6.7, 6.1, 6.4, 6.5, 5.2, 5.0, 5.2, 4.9, 4.7, 5.1]
    },
    {
      "name": "Pennsylvania",
      "code": "PA",
      "rates": [4.9, 5.3, 5.1, 5.2, 5.2, 6.1, 6.0, 5.8, 5.7, 5.3, 5.1, 5.0, 5.5, 4.8, 4.8]
    },
    {
      "name": "Indiana",
      "code": "IN",
      "rates": [5.8, 6.7, 5.9, 5.5, 5.1, 5.7, 5.7, 5.5, 5.0, 4.9, 4.1, 4.7, 4.7, 5.4, 5.0]
    },
    {
      "name": "Delaware",
      "code": "DE",
      "rates": [3.2, 2.9, 3.2, 2.6, 3.4, 4.4, 4.9, 4.5, 6.5, 4.6, 5.7, 5.3, 6.1, 4.4, 5.8]
    },
    {
      "name": "West Virginia",
      "code": "VW",
      "rates": [2.5, 2.2, 3.2, 4.0, 3.8, 4.5, 4.4, 3.6, 3.7, 4.6, 3.1, 4.7, 3.8, 3.3, 4.0]
    },
    {
      "name": "Ohio",
      "code": "OH",
      "rates": [3.7, 4.0, 4.6, 4.6, 4.4, 5.1, 4.9, 4.6, 4.8, 4.6, 4.2, 4.3, 4.1, 4.1, 4.0]
    },
    {
      "name": "Virginia",
      "code": "VA",
      "rates": [5.7, 5.1, 5.3, 5.6, 5.2, 6.1, 5.3, 5.4, 4.8, 4.7, 4.7, 3.8, 3.9, 3.9, 4.1]
    },
    {
      "name": "Kansas",
      "code": "KS",
      "rates": [6.3, 3.4, 2.9, 4.6, 4.5, 3.7, 4.5, 3.8, 4.0, 4.4, 3.4, 3.9, 2.9, 4.0, 3.1]
    },
    {
      "name": "Kentucky",
      "code": "KY",
      "rates": [4.8, 4.4, 4.7, 4.4, 5.7, 4.6, 4.1, 4.9, 4.7, 4.3, 4.3, 3.5, 4.6, 3.9, 3.6]
    },
    {
      "name": "New York",
      "code": "NY",
      "rates": [5.0, 5.0, 4.8, 4.9, 4.6, 4.5, 4.8, 4.2, 4.3, 4.0, 4.5, 3.9, 3.5, 3.3, 3.1]
    },
    {
      "name": "New Jersey",
      "code": "NJ",
      "rates": [3.4, 3.9, 4.0, 4.7, 4.5, 4.8, 4.9, 4.4, 4.3, 3.7, 4.2, 4.3, 4.4, 4.5, 3.9]
    },
    {
      "name": "Colorado",
      "code": "CO",
      "rates": [3.1, 3.6, 4.0, 4.1, 4.4, 3.7, 3.6, 3.2, 3.3, 3.2, 2.6, 3.0, 2.9, 3.3, 2.8]
    },
    {
      "name": "Alaska",
      "code": "AK",
      "rates": [4.3, 6.2, 5.1, 6.0, 5.6, 4.8, 5.4, 6.3, 3.9, 3.1, 4.3, 4.1, 4.1, 4.6, 5.6]
    },
    {
      "name": "Connecticut",
      "code": "CT",
      "rates": [2.9, 3.1, 2.4, 3.2, 2.9, 3.0, 3.9, 3.2, 3.8, 3.0, 3.7, 3.6, 3.3, 2.5, 2.4]
    },
    {
      "name": "Montana",
      "code": "MT",
      "rates": [2.2, 3.8, 1.8, 3.3, 3.2, 1.9, 3.5, 2.8, 4.1, 3.3, 2.5, 2.9, 2.9, 2.3, 3.6]
    },
    {
      "name": "Rhode Island",
      "code": "RI",
      "rates": [4.3, 3.7, 3.8, 2.3, 2.4, 3.2, 2.5, 1.8, 3.0, 3.0, 2.8, 1.9, 3.4, 2.9, 2.4]
    },
    {
      "name": "Washington",
      "code": "WA",
      "rates": [3.3, 3.0, 3.0, 3.0, 3.1, 3.3, 3.1, 2.7, 2.9, 2.9, 2.3, 2.4, 3.1, 2.4, 2.5]
    },
    {
      "name": "Massachusetts",
      "code": "MA",
      "rates": [2.0, 2.0, 2.2, 2.7, 2.2, 2.7, 2.8, 2.9, 2.9, 2.6, 3.3, 2.8, 1.8, 2.1, 2.0]
    },
    {
      "name": "South Dakota",
      "code": "SD",
      "rates": [0.9, 0.9, 1.4, 1.3, 2.2, 2.3, 3.8, 3.9, 4.6, 3.7, 2.8, 2.4, 2.8, 2.1, 2.3]
    },
    {
      "name": "Wisconsin",
      "code": "WI",
      "rates": [3.2, 3.6, 2.8, 3.3, 2.8, 3.7, 3.0, 3.3, 2.6, 2.6, 2.7, 2.4, 3.0, 2.8, 2.9]
    },
    {
      "name": "Wyoming",
      "code": "WY",
      "rates": [2.4, 1.8, 3.0, 2.8, 2.2, 2.8, 2.5, 4.0, 2.3, 2.0, 1.4, 3.2, 2.4, 2.9, 2.7]
    },
    {
      "name": "Nebraska",
      "code": "NE",
      "rates": [3.7, 2.5, 2.8, 3.2, 2.3, 2.5, 2.9, 4.0, 3.9, 2.3, 3.0, 3.7, 2.8, 3.0, 2.9]
    },
    {
      "name": "Oregon",
      "code": "OR",
      "rates": [2.0, 2.4, 2.0, 1.9, 2.5, 2.2, 2.4, 2.0, 2.3, 2.3, 2.5, 2.2, 2.3, 2.1, 2.0]
    },
    {
      "name": "Maine",
      "code": "ME",
      "rates": [1.2, 1.5, 1.1, 1.2, 1.4, 1.4, 1.7, 1.5, 2.4, 2.0, 1.8, 2.0, 2.0, 1.8, 1.6]
    },
    {
      "name": "Hawaii",
      "code": "HI",
      "rates": [2.9, 2.6, 1.9, 1.8, 2.6, 1.9, 1.6, 1.9, 2.0, 1.8, 1.8, 1.5, 1.5, 2.3, 1.8]
    },
    {
      "name": "North Dakota",
      "code": "ND",
      "rates": [0.6, 1.1, 0.8, 1.4, 1.3, 1.9, 2.2, 2.7, 1.7, 1.9, 1.5, 3.5, 3.6, 2.2, 3.0]
    },
    {
      "name": "Idaho",
      "code": "ID",
      "rates": [1.2, 2.3, 2.7, 1.9, 2.2, 2.4, 2.4, 3.3, 1.5, 1.6, 1.4, 2.2, 1.9, 1.8, 2.0]
    },
    {
      "name": "Minnesota",
      "code": "MN",
      "rates": [3.1, 2.4, 2.2, 2.5, 2.2, 2.2, 2.4, 2.2, 2.1, 1.4, 1.8, 1.4, 1.8, 2.1, 1.6]
    },
    {
      "name": "Utah",
      "code": "UT",
      "rates": [1.9, 2.9, 2.0, 2.6, 1.9, 2.2, 2.0, 2.2, 1.5, 1.4, 1.9, 1.8, 1.8, 1.8, 2.3]
    },
    {
      "name": "Iowa",
      "code": "IA",
      "rates": [1.6, 1.7, 1.5, 1.7, 1.5, 1.3, 1.8, 1.3, 2.6, 1.3, 1.2, 1.4, 1.6, 1.3, 1.9]
    },
    {
      "name": "Vermont",
      "code": "VT",
      "rates": [1.5, 1.1, 2.1, 2.4, 2.6, 1.3, 2.2, 2.1, 2.7, 1.3, 1.1, 1.8, 1.3, 1.6, 1.6]
    },
    {
      "name": "New Hampshire",
      "code": "NH",
      "rates": [1.8, 1.3, 0.9, 1.3, 1.3, 1.5, 1.0, 0.9, 1.1, 0.8, 1.0, 1.2, 1.1, 1.6, 0.9]
    },
    {
      "name": "Guam",
      "code": "GU",
      "rates": [null, null, null, 4.9, 5.4, 4.2, 6.4, 0.6, null, null, null, null, null, null, null]
    }
  ]
}
